pyeventdispatcher/__init__.py
pyeventdispatcher/event_dispatcher.py
test/__init__.py
test/test_pyeventdispatcher.py
pyeventdispatcher-0.2.3a0.dist-info/LICENSE
pyeventdispatcher-0.2.3a0.dist-info/METADATA
pyeventdispatcher-0.2.3a0.dist-info/WHEEL
pyeventdispatcher-0.2.3a0.dist-info/top_level.txt
pyeventdispatcher-0.2.3a0.dist-info/RECORD
