Metadata-Version: 2.1
Name: pyeventdispatcher
Version: 0.2.3a0
Summary: Your application components can communicate by sending and listening to events.
Home-page: https://github.com/whisller/pyeventdispatcher
Author: Daniel Ancuta
Author-email: whisller@gmail.com
License: MIT
Keywords: event dispatcher event-dispatcher
Platform: UNKNOWN
Classifier: Development Status :: 3 - Alpha
Classifier: Environment :: Other Environment
Classifier: Intended Audience :: Developers
Classifier: License :: OSI Approved :: MIT License
Classifier: Operating System :: OS Independent
Classifier: Programming Language :: Python
Classifier: Programming Language :: Python :: 3.6
Classifier: Programming Language :: Python :: 3.7
Classifier: Programming Language :: Python :: 3 :: Only
Classifier: Topic :: Software Development :: Libraries
Requires-Python: >=3.6
